{
  "finding_id": "pytorch_154312",
  "repo": "pytorch/pytorch",
  "issue_number": 154312,
  "issue_title": "torch.logdet produces incorrect results for singular matrices on CUDA vs CPU",
  "issue_url": "https://github.com/pytorch/pytorch/issues/154312",
  "issue_state": "OPEN",
  "issue_created_at": "2025-05-24T21:25:59Z",
  "issue_labels": [
    "high priority",
    "module: cuda",
    "triaged",
    "module: NaNs and Infs",
    "module: linear algebra",
    "module: correctness (silent)"
  ],
  "body_preview": "",
  "initial_classification": "correctness_silent",
  "surface_reasoning": "Priority 1: labeled `module: correctness (silent)` + `module: cuda` + `module: linear algebra` + `high priority`. Title: `torch.logdet` produces incorrect results for singular matrices on CUDA vs CPU \u2014 CUDA vs CPU numerical divergence in a core linear algebra op. Domain relevance: log-determinant on CUDA uses cuSOLVER LU factorization; incorrect results for singular matrices indicate a kernel-level handling bug in the CUDA linalg backend.",
  "stage": "raw",
  "linked_prs": null,
  "maintainer_signals": null,
  "blocking_signals": null,
  "fix_scope": null,
  "affected_hardware": null,
  "still_reproducible": null,
  "confidence": null,
  "confidence_justification": null,
  "recommended_action": null,
  "closest_ground_truth": null,
  "ground_truth_delta": null,
  "created_at": "2026-04-24T10:00:00Z",
  "updated_at": "2026-04-24T10:00:00Z"
}